{
 "cells": [
  {
   "cell_type": "markdown",
   "metadata": {},
   "source": [
    "Prerequisites: Yield Keyword and Iterators\n",
    "\n",
    "There are two terms involved when we discuss generators.\n",
    "\n",
    "    Generator-Function : A generator-function is defined like a normal function, but whenever it needs to generate a value, it does so with the yield keyword rather than return. If the body of a def contains yield, the function automatically becomes a generator function. "
   ]
  },
  {
   "cell_type": "code",
   "execution_count": 7,
   "metadata": {},
   "outputs": [
    {
     "name": "stdout",
     "output_type": "stream",
     "text": [
      "1\n",
      "2\n",
      "3\n"
     ]
    }
   ],
   "source": [
    "\n",
    "# A generator function that yields 1 for first time, \n",
    "# 2 second time and 3 third time \n",
    "def simpleGeneratorFun(): \n",
    "    yield 1            \n",
    "    yield 2            \n",
    "    yield 3\n",
    "\n",
    "#Driver code to check above generator function \n",
    "for value in simpleGeneratorFun():  \n",
    "    print(value) "
   ]
  },
  {
   "cell_type": "markdown",
   "metadata": {},
   "source": [
    "Generator-Object : Generator functions return a generator object. Generator objects are used either by calling the next method on the generator object or using the generator object in a “for in” loop (as shown in the above program). "
   ]
  },
  {
   "cell_type": "code",
   "execution_count": 21,
   "metadata": {},
   "outputs": [
    {
     "name": "stdout",
     "output_type": "stream",
     "text": [
      "5\n",
      "6\n",
      "7\n"
     ]
    },
    {
     "ename": "StopIteration",
     "evalue": "",
     "output_type": "error",
     "traceback": [
      "\u001b[1;31m---------------------------------------------------------------------------\u001b[0m",
      "\u001b[1;31mStopIteration\u001b[0m                             Traceback (most recent call last)",
      "\u001b[1;32m<ipython-input-21-15d0f34a77be>\u001b[0m in \u001b[0;36m<module>\u001b[1;34m\u001b[0m\n\u001b[0;32m      8\u001b[0m \u001b[0mprint\u001b[0m\u001b[1;33m(\u001b[0m\u001b[0ma\u001b[0m\u001b[1;33m.\u001b[0m\u001b[0m__next__\u001b[0m\u001b[1;33m(\u001b[0m\u001b[1;33m)\u001b[0m\u001b[1;33m)\u001b[0m\u001b[1;33m\u001b[0m\u001b[1;33m\u001b[0m\u001b[0m\n\u001b[0;32m      9\u001b[0m \u001b[0mprint\u001b[0m\u001b[1;33m(\u001b[0m\u001b[0ma\u001b[0m\u001b[1;33m.\u001b[0m\u001b[0m__next__\u001b[0m\u001b[1;33m(\u001b[0m\u001b[1;33m)\u001b[0m\u001b[1;33m)\u001b[0m\u001b[1;33m\u001b[0m\u001b[1;33m\u001b[0m\u001b[0m\n\u001b[1;32m---> 10\u001b[1;33m \u001b[0mprint\u001b[0m\u001b[1;33m(\u001b[0m\u001b[0ma\u001b[0m\u001b[1;33m.\u001b[0m\u001b[0m__next__\u001b[0m\u001b[1;33m(\u001b[0m\u001b[1;33m)\u001b[0m\u001b[1;33m)\u001b[0m\u001b[1;33m\u001b[0m\u001b[1;33m\u001b[0m\u001b[0m\n\u001b[0m",
      "\u001b[1;31mStopIteration\u001b[0m: "
     ]
    }
   ],
   "source": [
    "def anyfunc(x):\n",
    "    yield x\n",
    "    yield x+1\n",
    "    yield x+2\n",
    "    \n",
    "a=anyfunc(5)\n",
    "print(a.__next__())\n",
    "print(a.__next__())\n",
    "print(a.__next__())\n",
    "\n",
    "print(a.__next__())#4th call stops iteration"
   ]
  },
  {
   "cell_type": "markdown",
   "metadata": {},
   "source": [
    "So a generator function returns an generator object that is iterable, i.e., can be used as an Iterators .\n",
    "\n",
    "As another example, below is a generator for Fibonacci Numbers."
   ]
  },
  {
   "cell_type": "code",
   "execution_count": 29,
   "metadata": {},
   "outputs": [
    {
     "name": "stdout",
     "output_type": "stream",
     "text": [
      "0\n",
      "1\n",
      "1\n",
      "2\n",
      "3\n",
      "\n",
      "Using for in loop\n",
      "0\n",
      "1\n",
      "1\n",
      "2\n",
      "3\n"
     ]
    }
   ],
   "source": [
    "# A simple generator for Fibonacci Numbers \n",
    "def fib(limit): \n",
    "      \n",
    "    # Initialize first two Fibonacci Numbers  \n",
    "    a, b = 0, 1\n",
    "  \n",
    "    # One by one yield next Fibonacci Number \n",
    "    while a < limit: \n",
    "        yield a\n",
    "        a, b = b, a + b \n",
    "\n",
    "# Create a generator object \n",
    "x = fib(5) \n",
    "  \n",
    "# Iterating over the generator object using next \n",
    "print(x.__next__())\n",
    "print(x.__next__())\n",
    "print(x.__next__())\n",
    "print(x.__next__())\n",
    "print(x.__next__())\n",
    "  \n",
    "print(\"\\nUsing for in loop\") \n",
    "for i in fib(5):  \n",
    "    print(i)"
   ]
  },
  {
   "cell_type": "code",
   "execution_count": 26,
   "metadata": {},
   "outputs": [
    {
     "name": "stdout",
     "output_type": "stream",
     "text": [
      "  5           0 LOAD_CONST               1 ((0, 1))\n",
      "              2 UNPACK_SEQUENCE          2\n",
      "              4 STORE_FAST               1 (a)\n",
      "              6 STORE_FAST               2 (b)\n",
      "\n",
      "  8           8 SETUP_LOOP              32 (to 42)\n",
      "        >>   10 LOAD_FAST                1 (a)\n",
      "             12 LOAD_FAST                0 (limit)\n",
      "             14 COMPARE_OP               0 (<)\n",
      "             16 POP_JUMP_IF_FALSE       40\n",
      "\n",
      "  9          18 LOAD_FAST                1 (a)\n",
      "             20 YIELD_VALUE\n",
      "             22 POP_TOP\n",
      "\n",
      " 10          24 LOAD_FAST                2 (b)\n",
      "             26 LOAD_FAST                1 (a)\n",
      "             28 LOAD_FAST                2 (b)\n",
      "             30 BINARY_ADD\n",
      "             32 ROT_TWO\n",
      "             34 STORE_FAST               1 (a)\n",
      "             36 STORE_FAST               2 (b)\n",
      "             38 JUMP_ABSOLUTE           10\n",
      "        >>   40 POP_BLOCK\n",
      "        >>   42 LOAD_CONST               0 (None)\n",
      "             44 RETURN_VALUE\n"
     ]
    }
   ],
   "source": [
    "import dis\n",
    "dis.dis(fib)"
   ]
  },
  {
   "cell_type": "code",
   "execution_count": null,
   "metadata": {},
   "outputs": [],
   "source": []
  },
  {
   "cell_type": "code",
   "execution_count": null,
   "metadata": {},
   "outputs": [],
   "source": []
  },
  {
   "cell_type": "code",
   "execution_count": null,
   "metadata": {},
   "outputs": [],
   "source": []
  }
 ],
 "metadata": {
  "kernelspec": {
   "display_name": "Python 3",
   "language": "python",
   "name": "python3"
  },
  "language_info": {
   "codemirror_mode": {
    "name": "ipython",
    "version": 3
   },
   "file_extension": ".py",
   "mimetype": "text/x-python",
   "name": "python",
   "nbconvert_exporter": "python",
   "pygments_lexer": "ipython3",
   "version": "3.7.3"
  }
 },
 "nbformat": 4,
 "nbformat_minor": 2
}
